{"_id":{"$oid":"59208eebb81442152048611b"},"tag":"intel","__v":0}
{"_id":{"$oid":"59208eebb814421520486119"},"tag":"программирование","__v":0}
{"_id":{"$oid":"59208eebb81442152048611a"},"tag":"процессоры","__v":0}
{"_id":{"$oid":"59208eebb814421520486120"},"tag":"полёт на луну","__v":0}
{"_id":{"$oid":"59208eebb814421520486125"},"tag":"шифрование","__v":0}
{"_id":{"$oid":"59208eebb81442152048612a"},"tag":"антропоцен","__v":0}
{"_id":{"$oid":"59208eebb814421520486118"},"tag":"JDK 10","__v":0}
{"_id":{"$oid":"59208eebb81442152048612f"},"tag":"биотехнологии","__v":0}
{"_id":{"$oid":"59208eebb814421520486134"},"tag":"потрачено","__v":0}
{"_id":{"$oid":"59208eebb814421520486117"},"tag":"java","__v":0}
{"_id":{"$oid":"59208eebb81442152048611d"},"tag":"JDK 9","__v":0}
{"_id":{"$oid":"59208eebb81442152048611c"},"tag":"intel atom","__v":0}
{"_id":{"$oid":"59208eebb814421520486122"},"tag":"spacex","__v":0}
{"_id":{"$oid":"59208eebb814421520486139"},"tag":"робототехника","__v":0}
{"_id":{"$oid":"59208eebb814421520486127"},"tag":"eff","__v":0}
{"_id":{"$oid":"59208eebb814421520486121"},"tag":"НАСА","__v":0}
{"_id":{"$oid":"59208eebb81442152048613e"},"tag":"энергетика","__v":0}
{"_id":{"$oid":"59208eebb81442152048612c"},"tag":"сотовая связь","__v":0}
{"_id":{"$oid":"59208eebb814421520486143"},"tag":"машинное обучение","__v":0}
{"_id":{"$oid":"59208eebb814421520486126"},"tag":"https","__v":0}
{"_id":{"$oid":"59208eebb814421520486131"},"tag":"мозг","__v":0}
{"_id":{"$oid":"59208eebb81442152048612b"},"tag":"5g","__v":0}
{"_id":{"$oid":"59208eebb814421520486148"},"tag":"сноуден","__v":0}
{"_id":{"$oid":"59208eebb814421520486136"},"tag":"астрономия","__v":0}
{"_id":{"$oid":"59208eebb814421520486130"},"tag":"мыши","__v":0}
{"_id":{"$oid":"59208eebb81442152048614d"},"tag":"автопилот","__v":0}
{"_id":{"$oid":"59208eebb81442152048613b"},"tag":"будущее","__v":0}
{"_id":{"$oid":"59208eebb814421520486135"},"tag":"NASA","__v":0}
{"_id":{"$oid":"59208eebb81442152048611f"},"tag":"луна","__v":0}
{"_id":{"$oid":"59208eebb814421520486140"},"tag":"мобильная реклама","__v":0}
{"_id":{"$oid":"59208eebb81442152048613a"},"tag":"китай","__v":0}
{"_id":{"$oid":"59208eebb81442152048611e"},"tag":"космонавтика","__v":0}
{"_id":{"$oid":"59208eebb814421520486124"},"tag":"безопасность","__v":0}
{"_id":{"$oid":"59208eebb814421520486123"},"tag":"утечка","__v":0}
{"_id":{"$oid":"59208eebb81442152048613f"},"tag":"google","__v":0}
{"_id":{"$oid":"59208eebb814421520486129"},"tag":"Земля","__v":0}
{"_id":{"$oid":"59208eebb814421520486128"},"tag":"экология","__v":0}
{"_id":{"$oid":"59208eebb81442152048612e"},"tag":"exynos","__v":0}
{"_id":{"$oid":"59208eebb81442152048612d"},"tag":"samsung","__v":0}
{"_id":{"$oid":"59208eebb814421520486144"},"tag":"космонавтика","__v":0}
{"_id":{"$oid":"59208eebb814421520486133"},"tag":"неудача","__v":0}
{"_id":{"$oid":"59208eebb814421520486132"},"tag":"физика","__v":0}
{"_id":{"$oid":"59208eebb814421520486149"},"tag":"эдвард сноуден","__v":0}
{"_id":{"$oid":"59208eebb814421520486138"},"tag":"экзопланеты","__v":0}
{"_id":{"$oid":"59208eebb814421520486137"},"tag":"космос","__v":0}
{"_id":{"$oid":"59208eebb81442152048614e"},"tag":"автомобили","__v":0}
{"_id":{"$oid":"59208eebb81442152048613d"},"tag":"авария","__v":0}
{"_id":{"$oid":"59208eebb81442152048613c"},"tag":"АЭС","__v":0}
{"_id":{"$oid":"59208eebb814421520486141"},"tag":"ии","__v":0}
{"_id":{"$oid":"59208eebb814421520486142"},"tag":"нейронные сети","__v":0}
{"_id":{"$oid":"59208eebb814421520486147"},"tag":"психология","__v":0}
{"_id":{"$oid":"59208eebb814421520486146"},"tag":"ложь","__v":0}
{"_id":{"$oid":"59208eebb81442152048614b"},"tag":"тесла","__v":0}
{"_id":{"$oid":"59208eebb81442152048614c"},"tag":"tesla","__v":0}
{"_id":{"$oid":"59208eebb814421520486145"},"tag":"отказ","__v":0}
{"_id":{"$oid":"59208eebb81442152048614a"},"tag":"гражданство РФ","__v":0}
{"_id":{"$oid":"59208eebb81442152048614f"},"tag":"расследование","__v":0}
